nanofed/__init__.py
nanofed/communication/__init__.py
nanofed/communication/http/__init__.py
nanofed/communication/http/client.py
nanofed/communication/http/server.py
nanofed/communication/http/types.py
nanofed/core/__init__.py
nanofed/core/exceptions.py
nanofed/core/interfaces.py
nanofed/core/types.py
nanofed/data/__init__.py
nanofed/data/mnist.py
nanofed/models/__init__.py
nanofed/models/mnist.py
nanofed/orchestration/__init__.py
nanofed/orchestration/coordinator.py
nanofed/orchestration/types.py
nanofed/orchestration/utils.py
nanofed/server/__init__.py
nanofed/server/aggregator/__init__.py
nanofed/server/aggregator/base.py
nanofed/server/aggregator/fedavg.py
nanofed/server/model_manager/__init__.py
nanofed/server/model_manager/manager.py
nanofed/trainer/__init__.py
nanofed/trainer/base.py
nanofed/trainer/callback.py
nanofed/trainer/torch.py
nanofed/utils/__init__.py
nanofed/utils/dates.py
nanofed/utils/logger.py
nanofed-0.1.4.dist-info/LICENSE
nanofed-0.1.4.dist-info/METADATA
nanofed-0.1.4.dist-info/WHEEL
nanofed-0.1.4.dist-info/entry_points.txt
nanofed-0.1.4.dist-info/RECORD
